dept/__init__.py
dept/base.py
dept/datetime.py
dept/numeric.py
dept/py.typed
dept/re.py
dept/sized.py
tests/__init__.py
tests/test_datetime.py
tests/test_numeric.py
tests/test_re.py
tests/test_sized.py
dependent_types-0.0.1.dist-info/LICENSE
dependent_types-0.0.1.dist-info/METADATA
dependent_types-0.0.1.dist-info/WHEEL
dependent_types-0.0.1.dist-info/top_level.txt
dependent_types-0.0.1.dist-info/RECORD
