Metadata-Version: 2.1
Name: dependent-types
Version: 0.0.1
Summary: Dependent types for Python
Home-page: https://github.com/antonagestam/dependent-types/
Author: Anton Agestam
Author-email: git@antonagestam.se
License: MIT License
Platform: UNKNOWN
Classifier: Intended Audience :: Developers
Classifier: Operating System :: OS Independent
Classifier: Programming Language :: Python
Classifier: Programming Language :: Python :: 3
Classifier: Programming Language :: Python :: 3.8
Classifier: Development Status :: 3 - Alpha
Requires-Python: >=3.8
Provides-Extra: test
Requires-Dist: black ; extra == 'test'
Requires-Dist: flake8 ; extra == 'test'
Requires-Dist: mypy ; extra == 'test'
Requires-Dist: sorti ; extra == 'test'
Requires-Dist: pytest ; extra == 'test'
Requires-Dist: pytest-mypy-plugins ; extra == 'test'
